smsfly/__init__.py
smsfly/errors.py
smsfly/smsfly.py
smsfly/util.py
smsfly/versiontools.py
tests/.gitdir
tests/api_test.py
SMSFly-0.1.6.dist-info/LICENSE.rst
SMSFly-0.1.6.dist-info/METADATA
SMSFly-0.1.6.dist-info/WHEEL
SMSFly-0.1.6.dist-info/top_level.txt
SMSFly-0.1.6.dist-info/RECORD
