Metadata-Version: 2.1
Name: SMSFly
Version: 0.1.6
Summary: Python wrapper for SMS-Fly gateway API
Home-page: https://github.com/open-craft-guild/python-smsfly
Author: Sviatoslav Sydorenko (@webknjaz) <wk+open-craft-guild@sydorenko.org.ua>, Anna Kurylo <anna.kurilo21+open-craft-guild@gmail.com>
Author-email: wk+open-craft-guild@sydorenko.org.ua
License: MIT
Project-URL: Bug Tracker, https://github.com/open-craft-guild/python-smsfly/issues
Project-URL: CI: Travis, https://travis-ci.org/open-craft-guild/python-smsfly
Project-URL: Source Code, https://github.com/open-craft-guild/python-smsfly
Keywords: api,sms,gateway,sms-fly,requests,xml
Platform: UNKNOWN
Classifier: Development Status :: 3 - Alpha
Classifier: Environment :: Plugins
Classifier: Environment :: Web Environment
Classifier: Intended Audience :: Developers
Classifier: License :: OSI Approved :: MIT License
Classifier: Operating System :: OS Independent
Classifier: Programming Language :: Python
Classifier: Programming Language :: Python :: 3
Classifier: Programming Language :: Python :: 3.5
Classifier: Programming Language :: Python :: 3.6
Classifier: Programming Language :: Python :: 3.7
Classifier: Programming Language :: Python :: 3.8
Classifier: Programming Language :: Python :: Implementation :: CPython
Classifier: Programming Language :: Python :: Implementation :: PyPy
Classifier: Topic :: Internet :: WWW/HTTP
Classifier: Topic :: Internet :: WWW/HTTP :: Session
Classifier: Topic :: Software Development
Classifier: Topic :: Software Development :: Libraries
Classifier: Topic :: Software Development :: Libraries :: Python Modules
Requires-Python: >=3.5
Requires-Dist: beautifulsoup4[lxml] (==4.5.3)
Requires-Dist: requests (==2.13.0)
